c1algo2/__init__.py
c1algo2/data.py
c1algo2/evaluator.py
c1algo2/forecaster.py
tools/GraphingTools/correlation.py
tools/GraphingTools/graph.py
c1algo2-1.0.1.dist-info/METADATA
c1algo2-1.0.1.dist-info/WHEEL
c1algo2-1.0.1.dist-info/top_level.txt
c1algo2-1.0.1.dist-info/RECORD
